tetgen/__init__.py
tetgen/_tetgen.cpython-311-x86_64-linux-gnu.so
tetgen/_version.py
tetgen/pytetgen.py
tetgen-0.6.7.dist-info/METADATA
tetgen-0.6.7.dist-info/WHEEL
tetgen-0.6.7.dist-info/top_level.txt
tetgen-0.6.7.dist-info/RECORD
tetgen-0.6.7.dist-info/licenses/LICENSE
